UPAFuzzySystems/UPAFuzzySystems.py
UPAFuzzySystems/__init__.py
UPAFuzzySystems-0.2.4.dist-info/LICENSE
UPAFuzzySystems-0.2.4.dist-info/METADATA
UPAFuzzySystems-0.2.4.dist-info/WHEEL
UPAFuzzySystems-0.2.4.dist-info/top_level.txt
UPAFuzzySystems-0.2.4.dist-info/RECORD
