Metadata-Version: 2.1
Name: UPAFuzzySystems
Version: 0.2.4
Summary: UPAFuzzySystems package for definition and simulation of Fuzzy Inference Systems for general and control applications.
Home-page: https://github.com/UniversidadPolitecnicaAguascalientes/UPAFuzzySystems/
Author: Dr. Martin Montes Rivera (Universidad Politécnica de Aguascalientes)
Author-email: <martin.montes@upa.edu.mx>
License: MIT
Keywords: python,fuzzy logic,fuzzy control,fuzzy inference systems,artificial intelligence
Classifier: Development Status :: 4 - Beta
Classifier: Intended Audience :: Education
Classifier: Programming Language :: Python :: 3
Classifier: Operating System :: Unix
Classifier: Operating System :: MacOS :: MacOS X
Classifier: Operating System :: Microsoft :: Windows
License-File: LICENSE
Requires-Dist: numpy
Requires-Dist: matplotlib
Requires-Dist: control
Requires-Dist: scikit-fuzzy
